{
	"info": {
		"_postman_id": "6afdc7d2-b511-4608-86ff-d48b7feb9da6",
		"name": "b2bShopApi",
		"schema": "https://schema.getpostman.com/json/collection/v2.1.0/collection.json",
		"_exporter_id": "34110969"
	},
	"item": [
		{
			"name": "Shop",
			"item": [
				{
					"name": "get Shop",
					"request": {
						"auth": {
							"type": "bearer",
							"bearer": [
								{
									"key": "token",
									"value": "{{bearer_token}}",
									"type": "string"
								}
							]
						},
						"method": "GET",
						"header": [],
						"url": {
							"raw": "{{baseurl}}/shop",
							"host": [
								"{{baseurl}}"
							],
							"path": [
								"shop"
							]
						}
					},
					"response": []
				},
				{
					"name": "get ShopById",
					"request": {
						"auth": {
							"type": "bearer",
							"bearer": [
								{
									"key": "token",
									"value": "{{bearer_token}}",
									"type": "string"
								}
							]
						},
						"method": "GET",
						"header": [],
						"url": {
							"raw": "{{baseurl}}/shop/1",
							"host": [
								"{{baseurl}}"
							],
							"path": [
								"shop",
								"1"
							]
						}
					},
					"response": []
				},
				{
					"name": "create singleShop",
					"request": {
						"auth": {
							"type": "bearer",
							"bearer": [
								{
									"key": "token",
									"value": "{{bearer_token}}",
									"type": "string"
								}
							]
						},
						"method": "POST",
						"header": [],
						"body": {
							"mode": "raw",
							"raw": "{\r\n    \"name\": \"first shop\",\r\n    \"email\": \"firstshop@mail.com\",\r\n    \"phoneNumber\": \"05678478961\",\r\n    \"vatNumber\": \"first vatNumber\",\r\n    \"aboutUs\": \"first aboutUs\",\r\n    \"privacyPolicy\": \"first privacyPolicy\"\r\n}",
							"options": {
								"raw": {
									"language": "json"
								}
							}
						},
						"url": {
							"raw": "{{baseurl}}/shop",
							"host": [
								"{{baseurl}}"
							],
							"path": [
								"shop"
							]
						}
					},
					"response": []
				},
				{
					"name": "create multipleShops",
					"request": {
						"auth": {
							"type": "bearer",
							"bearer": [
								{
									"key": "token",
									"value": "{{bearer_token}}",
									"type": "string"
								}
							]
						},
						"method": "POST",
						"header": [],
						"body": {
							"mode": "raw",
							"raw": "[\r\n    {\r\n        \"name\": \"first shop\",\r\n        \"email\": \"firstshop@mail.com\",\r\n        \"phoneNumber\": \"05678478961\",\r\n        \"vatNumber\": \"1 vatNumber\",\r\n        \"aboutUs\": \"1 aboutUs\",\r\n        \"privacyPolicy\": \"1 privacyPolicy\"\r\n    },\r\n    {\r\n        \"name\": \"second shop\",\r\n        \"email\": \"secondshop@mail.com\",\r\n        \"phoneNumber\": \"05678478962\",\r\n        \"vatNumber\": \"2 vatNumber\",\r\n        \"aboutUs\": \"2 aboutUs\",\r\n        \"privacyPolicy\": \"privacyPolicy\"\r\n    },\r\n    {\r\n        \"name\": \"third shop\",\r\n        \"email\": \"thirdshop@mail.com\",\r\n        \"phoneNumber\": \"05678478963\",\r\n        \"vatNumber\": \"3 vatNumber\",\r\n        \"aboutUs\": \"3 aboutUs\",\r\n        \"privacyPolicy\": \"3 privacyPolicy\"\r\n    },\r\n    {\r\n        \"name\": \"fourth shop\",\r\n        \"email\": \"fourthshop@mail.com\",\r\n        \"phoneNumber\": \"05678478964\",\r\n        \"vatNumber\": \"4 vatNumber\",\r\n        \"aboutUs\": \"4 aboutUs\",\r\n        \"privacyPolicy\": \"4 privacyPolicy\"\r\n    }\r\n]",
							"options": {
								"raw": {
									"language": "json"
								}
							}
						},
						"url": {
							"raw": "{{baseurl}}/shop",
							"host": [
								"{{baseurl}}"
							],
							"path": [
								"shop"
							]
						}
					},
					"response": []
				},
				{
					"name": "update ShopById",
					"request": {
						"auth": {
							"type": "bearer",
							"bearer": [
								{
									"key": "token",
									"value": "{{bearer_token}}",
									"type": "string"
								}
							]
						},
						"method": "PUT",
						"header": [],
						"body": {
							"mode": "raw",
							"raw": "{\r\n    \"name\": \"first shop update test\",\r\n    \"email\": \"firstshopupdate test@mail.com\",\r\n    \"phoneNumber\": \"05678478961\",\r\n    \"vatNumber\": \"1 vatNumber update test\",\r\n    \"aboutUs\": \"1 aboutUs update test\",\r\n    \"privacyPolicy\": \"1 privacyPolicy update test\"\r\n}",
							"options": {
								"raw": {
									"language": "json"
								}
							}
						},
						"url": {
							"raw": "{{baseurl}}/shop/1",
							"host": [
								"{{baseurl}}"
							],
							"path": [
								"shop",
								"1"
							]
						}
					},
					"response": []
				},
				{
					"name": "delete Shop",
					"request": {
						"auth": {
							"type": "bearer",
							"bearer": [
								{
									"key": "token",
									"value": "{{bearer_token}}",
									"type": "string"
								}
							]
						},
						"method": "DELETE",
						"header": [],
						"body": {
							"mode": "raw",
							"raw": "{\r\n    \"ids\":[1,2]\r\n}",
							"options": {
								"raw": {
									"language": "json"
								}
							}
						},
						"url": {
							"raw": "{{baseurl}}/shop",
							"host": [
								"{{baseurl}}"
							],
							"path": [
								"shop"
							]
						}
					},
					"response": []
				}
			]
		},
		{
			"name": "Customer",
			"item": [
				{
					"name": "get AllCustomers",
					"request": {
						"auth": {
							"type": "bearer",
							"bearer": [
								{
									"key": "token",
									"value": "{{bearer_token}}",
									"type": "string"
								}
							]
						},
						"method": "GET",
						"header": [],
						"url": {
							"raw": "{{baseurl}}/customer",
							"host": [
								"{{baseurl}}"
							],
							"path": [
								"customer"
							]
						}
					},
					"response": []
				},
				{
					"name": "get CustomerById",
					"request": {
						"auth": {
							"type": "bearer",
							"bearer": [
								{
									"key": "token",
									"value": "{{bearer_token}}",
									"type": "string"
								}
							]
						},
						"method": "GET",
						"header": [],
						"url": {
							"raw": "{{baseurl}}/customer/1",
							"host": [
								"{{baseurl}}"
							],
							"path": [
								"customer",
								"1"
							]
						}
					},
					"response": []
				},
				{
					"name": "create singleCustomer",
					"request": {
						"auth": {
							"type": "bearer",
							"bearer": [
								{
									"key": "token",
									"value": "{{bearer_token}}",
									"type": "string"
								}
							]
						},
						"method": "POST",
						"header": [],
						"body": {
							"mode": "raw",
							"raw": "{\r\n    \"name\": \"first customer\",\r\n    \"email\": \"firstcustomer@mail.com\",\r\n    \"vatNumber\": \"first vatNumber\",\r\n    \"phoneNumber\": \"05678478965\",\r\n    \"isActive\": true\r\n}",
							"options": {
								"raw": {
									"language": "json"
								}
							}
						},
						"url": {
							"raw": "{{baseurl}}/customer",
							"host": [
								"{{baseurl}}"
							],
							"path": [
								"customer"
							]
						}
					},
					"response": []
				},
				{
					"name": "create multipleCustomers",
					"request": {
						"auth": {
							"type": "bearer",
							"bearer": [
								{
									"key": "token",
									"value": "{{bearer_token}}",
									"type": "string"
								}
							]
						},
						"method": "POST",
						"header": [],
						"body": {
							"mode": "raw",
							"raw": "[\r\n    {\r\n        \"name\": \"first customer\",\r\n        \"email\": \"firstcustomer@mail.com\",\r\n        \"shop\": {\r\n            \"tenantId\": 1\r\n        },\r\n        \"vatNumber\": \"first vatNumber\",\r\n        \"phoneNumber\": \"05678478961\",\r\n        \"isActive\": true\r\n    },\r\n    {\r\n        \"name\": \"second customer\",\r\n        \"email\": \"secondcustomer@mail.com\",\r\n        \"shop\": {\r\n            \"tenantId\": 2\r\n        },\r\n        \"vatNumber\": \"second vatNumber\",\r\n        \"phoneNumber\": \"05678478962\",\r\n        \"isActive\": true\r\n    },\r\n    {\r\n        \"name\": \"third customer\",\r\n        \"email\": \"thirdcustomer@mail.com\",\r\n        \"shop\": {\r\n            \"tenantId\": 3\r\n        },\r\n        \"vatNumber\": \"thirt vatNumber\",\r\n        \"phoneNumber\": \"05678478963\",\r\n        \"isActive\": true\r\n    },\r\n    {\r\n        \"name\": \"fourth customer\",\r\n        \"email\": \"fourthcustomer@mail.com\",\r\n        \"shop\": {\r\n            \"tenantId\": 4\r\n        },\r\n        \"vatNumber\": \"fourth vatNumber\",\r\n        \"phoneNumber\": \"05678478964\",\r\n        \"isActive\": false\r\n    }\r\n]",
							"options": {
								"raw": {
									"language": "json"
								}
							}
						},
						"url": {
							"raw": "{{baseurl}}/customer",
							"host": [
								"{{baseurl}}"
							],
							"path": [
								"customer"
							]
						}
					},
					"response": []
				},
				{
					"name": "update CustomerById",
					"request": {
						"auth": {
							"type": "bearer",
							"bearer": [
								{
									"key": "token",
									"value": "{{bearer_token}}",
									"type": "string"
								}
							]
						},
						"method": "PUT",
						"header": [],
						"body": {
							"mode": "raw",
							"raw": "{\r\n    \"tenantId\": 1,\r\n    \"name\": \"test for update customer\",\r\n    \"email\": \"firstcustomer@mail.com\",\r\n    \"shop\": {\r\n        \"tenantId\": 2\r\n    },\r\n    \"vatNumber\": \"first vatNumber\",\r\n    \"phoneNumber\": \"05678478961\",\r\n    \"active\": true\r\n}",
							"options": {
								"raw": {
									"language": "json"
								}
							}
						},
						"url": {
							"raw": "{{baseurl}}/customer/1",
							"host": [
								"{{baseurl}}"
							],
							"path": [
								"customer",
								"1"
							]
						}
					},
					"response": []
				},
				{
					"name": "delete Customer",
					"request": {
						"auth": {
							"type": "bearer",
							"bearer": [
								{
									"key": "token",
									"value": "{{bearer_token}}",
									"type": "string"
								}
							]
						},
						"method": "DELETE",
						"header": [],
						"body": {
							"mode": "raw",
							"raw": "",
							"options": {
								"raw": {
									"language": "json"
								}
							}
						},
						"url": {
							"raw": "{{baseurl}}/customer/1",
							"host": [
								"{{baseurl}}"
							],
							"path": [
								"customer",
								"1"
							]
						}
					},
					"response": []
				}
			]
		},
		{
			"name": "User",
			"item": [
				{
					"name": "get AllUsers",
					"request": {
						"auth": {
							"type": "bearer",
							"bearer": [
								{
									"key": "token",
									"value": "{{bearer_token}}",
									"type": "string"
								}
							]
						},
						"method": "GET",
						"header": [],
						"url": {
							"raw": "{{baseurl}}/user",
							"host": [
								"{{baseurl}}"
							],
							"path": [
								"user"
							]
						}
					},
					"response": []
				},
				{
					"name": "getMe",
					"request": {
						"auth": {
							"type": "bearer",
							"bearer": [
								{
									"key": "token",
									"value": "{{bearer_token}}",
									"type": "string"
								}
							]
						},
						"method": "GET",
						"header": [],
						"url": {
							"raw": "{{baseurl}}/user/me",
							"host": [
								"{{baseurl}}"
							],
							"path": [
								"user",
								"me"
							]
						}
					},
					"response": []
				},
				{
					"name": "get userById",
					"request": {
						"auth": {
							"type": "bearer",
							"bearer": [
								{
									"key": "token",
									"value": "{{bearer_token}}",
									"type": "string"
								}
							]
						},
						"method": "GET",
						"header": [],
						"url": {
							"raw": "{{baseurl}}/user/9898",
							"host": [
								"{{baseurl}}"
							],
							"path": [
								"user",
								"9898"
							]
						}
					},
					"response": []
				},
				{
					"name": "create singleUser",
					"request": {
						"auth": {
							"type": "bearer",
							"bearer": [
								{
									"key": "token",
									"value": "{{bearer_token}}",
									"type": "string"
								}
							]
						},
						"method": "POST",
						"header": [],
						"body": {
							"mode": "raw",
							"raw": "{\r\n    \"name\": \"Mahmut\",\r\n    \"username\": \"mahmut\",\r\n    \"password\": \"pass\",\r\n    \"email\": \"mahmut@email.com\",\r\n    \"phoneNumber\": \"05369874513\",\r\n    \"authorities\": [\r\n        \"ROLE_CUSTOMER_USER\"\r\n    ],\r\n    \"customer\": {\r\n        \"tenantId\": 5\r\n    }\r\n}",
							"options": {
								"raw": {
									"language": "json"
								}
							}
						},
						"url": {
							"raw": "{{baseurl}}/user",
							"host": [
								"{{baseurl}}"
							],
							"path": [
								"user"
							]
						}
					},
					"response": []
				},
				{
					"name": "create multipleUsers",
					"request": {
						"auth": {
							"type": "bearer",
							"bearer": [
								{
									"key": "token",
									"value": "{{bearer_token}}",
									"type": "string"
								}
							]
						},
						"method": "POST",
						"header": [],
						"body": {
							"mode": "raw",
							"raw": "[\r\n    {\r\n        \"name\": \"Ali\",\r\n        \"username\": \"ali\",\r\n        \"password\": \"pass\",\r\n        \"email\": \"ali@email.com\",\r\n        \"phoneNumber\": \"05369874501\",\r\n        \"authorities\": [\r\n            \"ROLE_SHOP_OWNER\"\r\n        ],\r\n        \"shop\": {\r\n            \"tenantId\": 1\r\n        }\r\n    },\r\n    {\r\n        \"name\": \"Aysu\",\r\n        \"username\": \"aysu\",\r\n        \"password\": \"pass\",\r\n        \"email\": \"aysu@email.com\",\r\n        \"phoneNumber\": \"05369874502\",\r\n        \"authorities\": [\r\n            \"ROLE_SHOP_OWNER\"\r\n        ],\r\n        \"shop\": {\r\n            \"tenantId\": 2\r\n        }\r\n    },\r\n    {\r\n        \"name\": \"Ayşe\",\r\n        \"username\": \"ayse\",\r\n        \"password\": \"pass\",\r\n        \"email\": \"ayse@email.com\",\r\n        \"phoneNumber\": \"05369874503\",\r\n        \"authorities\": [\r\n            \"ROLE_SHOP_OWNER\"\r\n        ],\r\n        \"shop\": {\r\n            \"tenantId\": 3\r\n        }\r\n    },\r\n    {\r\n        \"name\": \"Fatma\",\r\n        \"username\": \"fatma\",\r\n        \"password\": \"pass\",\r\n        \"email\": \"fatma@email.com\",\r\n        \"phoneNumber\": \"05369874504\",\r\n        \"authorities\": [\r\n            \"ROLE_SHOP_OWNER\"\r\n        ],\r\n        \"shop\": {\r\n            \"tenantId\": 4\r\n        }\r\n    },\r\n    {\r\n        \"name\": \"Hatice\",\r\n        \"username\": \"hatice\",\r\n        \"password\": \"pass\",\r\n        \"email\": \"hatice@email.com\",\r\n        \"phoneNumber\": \"05369874505\",\r\n        \"authorities\": [\r\n            \"ROLE_CUSTOMER_USER\"\r\n        ],\r\n        \"customer\": {\r\n            \"tenantId\": 1\r\n        }\r\n    },\r\n    {\r\n        \"name\": \"Ahmet\",\r\n        \"username\": \"ahmet\",\r\n        \"password\": \"pass\",\r\n        \"email\": \"ahmet@email.com\",\r\n        \"phoneNumber\": \"05369874506\",\r\n        \"authorities\": [\r\n            \"ROLE_CUSTOMER_USER\"\r\n        ],\r\n        \"customer\": {\r\n            \"tenantId\": 2\r\n        }\r\n    },\r\n    {\r\n        \"name\": \"Merve\",\r\n        \"username\": \"merve\",\r\n        \"password\": \"pass\",\r\n        \"email\": \"merve@email.com\",\r\n        \"phoneNumber\": \"05369874507\",\r\n        \"authorities\": [\r\n            \"ROLE_CUSTOMER_USER\"\r\n        ],\r\n        \"customer\": {\r\n            \"tenantId\": 3\r\n        }\r\n    },\r\n    {\r\n        \"name\": \"Seda\",\r\n        \"username\": \"seda\",\r\n        \"password\": \"pass\",\r\n        \"email\": \"seda@email.com\",\r\n        \"phoneNumber\": \"05369874508\",\r\n        \"authorities\": [\r\n            \"ROLE_CUSTOMER_USER\"\r\n        ],\r\n        \"customer\": {\r\n            \"tenantId\": 1\r\n        }\r\n    },\r\n    {\r\n        \"name\": \"Basak\",\r\n        \"username\": \"basak\",\r\n        \"password\": \"pass\",\r\n        \"email\": \"basak@email.com\",\r\n        \"phoneNumber\": \"05369874509\",\r\n        \"authorities\": [\r\n            \"ROLE_CUSTOMER_USER\"\r\n        ],\r\n        \"customer\": {\r\n            \"tenantId\": 2\r\n        }\r\n    },\r\n    {\r\n        \"name\": \"Pelin\",\r\n        \"username\": \"pelin\",\r\n        \"password\": \"pass\",\r\n        \"email\": \"pelin@email.com\",\r\n        \"phoneNumber\": \"05369874510\",\r\n        \"authorities\": [\r\n            \"ROLE_CUSTOMER_USER\"\r\n        ],\r\n        \"customer\": {\r\n            \"tenantId\": 3\r\n        }\r\n    },\r\n    {\r\n        \"name\": \"Arda\",\r\n        \"username\": \"arda\",\r\n        \"password\": \"pass\",\r\n        \"email\": \"arda@email.com\",\r\n        \"phoneNumber\": \"05369874511\",\r\n        \"authorities\": [\r\n            \"ROLE_CUSTOMER_USER\"\r\n        ],\r\n        \"customer\": {\r\n            \"tenantId\": 4\r\n        }\r\n    },\r\n    {\r\n        \"name\": \"Akın\",\r\n        \"username\": \"akın\",\r\n        \"password\": \"pass\",\r\n        \"email\": \"akın@email.com\",\r\n        \"phoneNumber\": \"05369874512\",\r\n        \"authorities\": [\r\n            \"ROLE_CUSTOMER_USER\"\r\n        ],\r\n        \"customer\": {\r\n            \"tenantId\": 1\r\n        }\r\n    }\r\n]",
							"options": {
								"raw": {
									"language": "json"
								}
							}
						},
						"url": {
							"raw": "{{baseurl}}/user",
							"host": [
								"{{baseurl}}"
							],
							"path": [
								"user"
							]
						}
					},
					"response": []
				},
				{
					"name": "update UserById",
					"request": {
						"auth": {
							"type": "bearer",
							"bearer": [
								{
									"key": "token",
									"value": "{{bearer_token}}",
									"type": "string"
								}
							]
						},
						"method": "PUT",
						"header": [],
						"body": {
							"mode": "raw",
							"raw": "{\r\n    \"id\": 1,\r\n    \"name\": \"Hakan update test\",\r\n    \"username\": \"hakan\",\r\n    \"newPassword\": true,\r\n    \"password\": \"test\",\r\n    \"email\": \"hakan@email.com\",\r\n    \"phoneNumber\": null,\r\n    \"authorities\": [\r\n        \"ROLE_SYSTEM_OWNER\"\r\n    ],\r\n    \"shop\": null,\r\n    \"customer\": null,\r\n    \"accountNonLocked\": true,\r\n    \"accountNonExpired\": true,\r\n    \"credentialsNonExpired\": true,\r\n    \"enabled\": true,\r\n    \"active\": true\r\n}",
							"options": {
								"raw": {
									"language": "json"
								}
							}
						},
						"url": {
							"raw": "{{baseurl}}/user/1",
							"host": [
								"{{baseurl}}"
							],
							"path": [
								"user",
								"1"
							]
						}
					},
					"response": []
				},
				{
					"name": "update user Password",
					"request": {
						"auth": {
							"type": "bearer",
							"bearer": [
								{
									"key": "token",
									"value": "{{bearer_token}}",
									"type": "string"
								}
							]
						},
						"method": "PUT",
						"header": [],
						"body": {
							"mode": "raw",
							"raw": "{\r\n    \"existPassword\": \"pass\",\r\n    \"newPassword\": \"password\"\r\n}",
							"options": {
								"raw": {
									"language": "json"
								}
							}
						},
						"url": {
							"raw": "{{baseurl}}/user/updatePassword/37",
							"host": [
								"{{baseurl}}"
							],
							"path": [
								"user",
								"updatePassword",
								"37"
							]
						}
					},
					"response": []
				},
				{
					"name": "delete User",
					"request": {
						"auth": {
							"type": "bearer",
							"bearer": [
								{
									"key": "token",
									"value": "{{bearer_token}}",
									"type": "string"
								}
							]
						},
						"method": "DELETE",
						"header": [],
						"body": {
							"mode": "raw",
							"raw": "",
							"options": {
								"raw": {
									"language": "json"
								}
							}
						},
						"url": {
							"raw": "{{baseurl}}/user/1",
							"host": [
								"{{baseurl}}"
							],
							"path": [
								"user",
								"1"
							]
						}
					},
					"response": []
				}
			]
		},
		{
			"name": "Product",
			"item": [
				{
					"name": "get AllProducts",
					"protocolProfileBehavior": {
						"disableBodyPruning": true
					},
					"request": {
						"auth": {
							"type": "bearer",
							"bearer": [
								{
									"key": "token",
									"value": "{{bearer_token}}",
									"type": "string"
								}
							]
						},
						"method": "GET",
						"header": [],
						"body": {
							"mode": "raw",
							"raw": "",
							"options": {
								"raw": {
									"language": "json"
								}
							}
						},
						"url": {
							"raw": "{{baseurl}}/product",
							"host": [
								"{{baseurl}}"
							],
							"path": [
								"product"
							]
						}
					},
					"response": []
				},
				{
					"name": "get Brand's Products",
					"protocolProfileBehavior": {
						"disableBodyPruning": true
					},
					"request": {
						"auth": {
							"type": "bearer",
							"bearer": [
								{
									"key": "token",
									"value": "{{bearer_token}}",
									"type": "string"
								}
							]
						},
						"method": "GET",
						"header": [],
						"body": {
							"mode": "raw",
							"raw": "{\r\n    \"brandIds\": [2],\r\n    \"categoryId\": [\r\n        1\r\n    ]\r\n}",
							"options": {
								"raw": {
									"language": "json"
								}
							}
						},
						"url": {
							"raw": "{{baseurl}}/product",
							"host": [
								"{{baseurl}}"
							],
							"path": [
								"product"
							],
							"query": [
								{
									"key": "",
									"value": "2",
									"disabled": true
								}
							]
						}
					},
					"response": []
				},
				{
					"name": "get Categorie's Products",
					"request": {
						"auth": {
							"type": "bearer",
							"bearer": [
								{
									"key": "token",
									"value": "{{bearer_token}}",
									"type": "string"
								}
							]
						},
						"method": "GET",
						"header": [
							{
								"key": "Authorization",
								"value": "Bearer eyJhbGciOiJIUzI1NiJ9.eyJzdWIiOiJoYWthbnNob3BAbWFpbC5jb20iLCJpYXQiOjE3MTc4NDQ0MzksImV4cCI6MTcxNzg0ODAzOX0.9W1jFxwt300t10PY95V5CwsngaLhD1YGmg_YgLirBdQ"
							}
						],
						"url": {
							"raw": "{{baseurl}}/product?categoryId=3",
							"host": [
								"{{baseurl}}"
							],
							"path": [
								"product"
							],
							"query": [
								{
									"key": "categoryId",
									"value": "3"
								}
							]
						}
					},
					"response": []
				},
				{
					"name": "get Brand's  And Categories Products",
					"request": {
						"auth": {
							"type": "bearer",
							"bearer": [
								{
									"key": "token",
									"value": "{{bearer_token}}",
									"type": "string"
								}
							]
						},
						"method": "GET",
						"header": [
							{
								"key": "Authorization",
								"value": "Bearer eyJhbGciOiJIUzI1NiJ9.eyJzdWIiOiJoYWthbnNob3BAbWFpbC5jb20iLCJpYXQiOjE3MTc4NDQ0MzksImV4cCI6MTcxNzg0ODAzOX0.9W1jFxwt300t10PY95V5CwsngaLhD1YGmg_YgLirBdQ"
							}
						],
						"url": {
							"raw": "localhost:8080/api/product?brandId=2&categoryId=3",
							"host": [
								"localhost"
							],
							"port": "8080",
							"path": [
								"api",
								"product"
							],
							"query": [
								{
									"key": "brandId",
									"value": "2"
								},
								{
									"key": "categoryId",
									"value": "3"
								}
							]
						}
					},
					"response": []
				},
				{
					"name": "get AllProducts Copy",
					"protocolProfileBehavior": {
						"disableBodyPruning": true
					},
					"request": {
						"auth": {
							"type": "bearer",
							"bearer": [
								{
									"key": "token",
									"value": "{{bearer_token}}",
									"type": "string"
								}
							]
						},
						"method": "GET",
						"header": [],
						"body": {
							"mode": "raw",
							"raw": "",
							"options": {
								"raw": {
									"language": "json"
								}
							}
						},
						"url": {
							"raw": "{{baseurl}}/product/elektronik",
							"host": [
								"{{baseurl}}"
							],
							"path": [
								"product",
								"elektronik"
							]
						}
					},
					"response": []
				},
				{
					"name": "get ProductById",
					"request": {
						"auth": {
							"type": "bearer",
							"bearer": [
								{
									"key": "token",
									"value": "{{bearer_token}}",
									"type": "string"
								}
							]
						},
						"method": "GET",
						"header": [],
						"url": {
							"raw": "{{baseurl}}/product/3",
							"host": [
								"{{baseurl}}"
							],
							"path": [
								"product",
								"3"
							]
						}
					},
					"response": []
				},
				{
					"name": "create singleProduct",
					"request": {
						"auth": {
							"type": "bearer",
							"bearer": [
								{
									"key": "token",
									"value": "{{bearer_token}}",
									"type": "string"
								}
							]
						},
						"method": "POST",
						"header": [],
						"body": {
							"mode": "raw",
							"raw": "{\r\n    \"gtin\": \"51231234\",\r\n    \"images\": [\r\n        {\r\n            \"url\": \"https://firebasestorage.googleapis.com/v0/b/b2bshop-d0961.appspot.com/o/9ad184b0-d0ff-4bf9-906b-9bd1b5fbbf9e.jpg?alt=media\",\r\n            \"isThumbnail\": true\r\n        },\r\n        {\r\n            \"url\": \"https://firebasestorage.googleapis.com/v0/b/b2bshop-d0961.appspot.com/o/10747be1-e4e9-454d-81e2-c132dbe3b860.jpg?alt=media\",\r\n            \"isThumbnail\": false\r\n        }\r\n    ],\r\n    \"code\": \"1231513\",\r\n    \"salesPrice\": 35000.0,\r\n    \"vatRate\": 0.0,\r\n    \"description\": \"12. Nesil Intel® Core™ i7-12700H 45 Watt 12. Nesil Intel® Core™ i7-12700H 45 Watt 12. Nesil Intel® Core™ i7-12700H 4.70 Ghz’e kadar saat hızıyla 6 adet performans ve 8 adet verimlilik çekirdeğiyle hem performansta yeni bir standartı belirliyor hem de gündelik kullanımda enerji tüketimini düşürüyor.\",\r\n    \"grossPrice\": 40000.0,\r\n    \"active\": true,\r\n    \"name\": \"Monster Abra A5 Laptop\",\r\n    \"stock\": 10,\r\n    \"category\": {\r\n        \"name\": \"Oyun Bilgisayarı\",\r\n        \"parentCategory\": 1,\r\n        \"id\": 4,\r\n        \"isActive\": true\r\n    },\r\n    \"brand\": {\r\n        \"name\": \"Monster\",\r\n        \"id\": 1\r\n    }\r\n}",
							"options": {
								"raw": {
									"language": "json"
								}
							}
						},
						"url": {
							"raw": "{{baseurl}}/product",
							"host": [
								"{{baseurl}}"
							],
							"path": [
								"product"
							]
						}
					},
					"response": []
				},
				{
					"name": "create multipleProducts",
					"request": {
						"auth": {
							"type": "bearer",
							"bearer": [
								{
									"key": "token",
									"value": "{{bearer_token}}",
									"type": "string"
								}
							]
						},
						"method": "POST",
						"header": [],
						"body": {
							"mode": "raw",
							"raw": "[\r\n    {\r\n        \"name\": \"name of product1\",\r\n        \"description\": \"description of product1\",\r\n        \"salesPrice\": 47.0,\r\n        \"grossPrice\": 54.0,\r\n        \"vatRate\": 7,\r\n        \"code\": \"123asdwq\",\r\n        \"shop\": {\r\n            \"tenantId\": 1\r\n        },\r\n        \"gtin\": \"5445678901061\",\r\n        \"stock\": 8,\r\n        \"isActive\": true\r\n    },\r\n    {\r\n        \"name\": \"name of product2\",\r\n        \"description\": \"description of product2\",\r\n        \"salesPrice\": 37.0,\r\n        \"grossPrice\": 123.0,\r\n        \"vatRate\": 3,\r\n        \"code\": \"5123wq\",\r\n        \"shop\": {\r\n            \"tenantId\": 2\r\n        },\r\n        \"gtin\": \"1845123901001\",\r\n        \"stock\": 76,\r\n        \"isActive\": true\r\n    },\r\n    {\r\n        \"name\": \"name of product3\",\r\n        \"description\": \"description of product3\",\r\n        \"salesPrice\": 49.0,\r\n        \"grossPrice\": 56.0,\r\n        \"vatRate\": 12,\r\n        \"code\": \"asd123asd\",\r\n        \"shop\": {\r\n            \"tenantId\": 3\r\n        },\r\n        \"gtin\": \"5325678901001\",\r\n        \"stock\": 89,\r\n        \"isActive\": true\r\n    },\r\n    {\r\n        \"name\": \"name of product4\",\r\n        \"description\": \"description of product4\",\r\n        \"salesPrice\": 97.79,\r\n        \"grossPrice\": 123.56,\r\n        \"vatRate\": 31,\r\n        \"code\": \"gcdff213asd\",\r\n        \"shop\": {\r\n            \"tenantId\": 1\r\n        },\r\n        \"gtin\": \"1845523401001\",\r\n        \"stock\": 74,\r\n        \"isActive\": true\r\n    },\r\n    {\r\n        \"name\": \"name of product5\",\r\n        \"description\": \"description of product5\",\r\n        \"salesPrice\": 7.97,\r\n        \"grossPrice\": 17.46,\r\n        \"vatRate\": 24,\r\n        \"code\": \"ghjfgwr\",\r\n        \"shop\": {\r\n            \"tenantId\": 2\r\n        },\r\n        \"gtin\": \"18456784353054\",\r\n        \"stock\": 35,\r\n        \"isActive\": true\r\n    },\r\n    {\r\n        \"name\": \"name of product6\",\r\n        \"description\": \"description of product6\",\r\n        \"salesPrice\": 55.45,\r\n        \"grossPrice\": 61.78,\r\n        \"vatRate\": 14,\r\n        \"code\": \"asdasdwq\",\r\n        \"shop\": {\r\n            \"tenantId\": 4\r\n        },\r\n        \"gtin\": \"1235678901007\",\r\n        \"stock\": 75,\r\n        \"isActive\": true\r\n    },\r\n    {\r\n        \"name\": \"name of product7\",\r\n        \"description\": \"description of product7\",\r\n        \"salesPrice\": 117.09,\r\n        \"grossPrice\": 137.79,\r\n        \"vatRate\": 10,\r\n        \"code\": \"lkşçjkl\",\r\n        \"shop\": {\r\n            \"tenantId\": 3\r\n        },\r\n        \"gtin\": \"7645678901562\",\r\n        \"stock\": 63,\r\n        \"isActive\": true\r\n    },\r\n    {\r\n        \"name\": \"name of product8\",\r\n        \"description\": \"description of product8\",\r\n        \"salesPrice\": 67.3,\r\n        \"grossPrice\": 74.7,\r\n        \"vatRate\": 11,\r\n        \"code\": \"gdfgdfwq\",\r\n        \"shop\": {\r\n            \"tenantId\": 4\r\n        },\r\n        \"gtin\": \"9655678901046\",\r\n        \"stock\": 45,\r\n        \"isActive\": true\r\n    },\r\n    {\r\n        \"name\": \"name of product9\",\r\n        \"description\": \"description of product9\",\r\n        \"salesPrice\": 63.06,\r\n        \"grossPrice\": 68.07,\r\n        \"vatRate\": 13,\r\n        \"code\": \"jgfhwe213\",\r\n        \"shop\": {\r\n            \"tenantId\": 2\r\n        },\r\n        \"gtin\": \"1845678901001\",\r\n        \"stock\": 7,\r\n        \"isActive\": true\r\n    }\r\n]\r\n",
							"options": {
								"raw": {
									"language": "json"
								}
							}
						},
						"url": {
							"raw": "{{baseurl}}/product",
							"host": [
								"{{baseurl}}"
							],
							"path": [
								"product"
							]
						}
					},
					"response": []
				},
				{
					"name": "update ProductById",
					"request": {
						"auth": {
							"type": "bearer",
							"bearer": [
								{
									"key": "token",
									"value": "{{bearer_token}}",
									"type": "string"
								}
							]
						},
						"method": "PUT",
						"header": [],
						"body": {
							"mode": "raw",
							"raw": "{\r\n    \"gtin\": \"5123123123\",\r\n    \"images\": [\r\n        {\r\n            \"isThumbnail\": true,\r\n            \"id\": 3,\r\n            \"url\": \"https://firebasestorage.googleapis.com/v0/b/b2bshop-d0961.appspot.com/o/9ad184b0-d0ff-4bf9-906b-9bd1b5fbbf9e.jpg?alt=media\"\r\n        },\r\n        {\r\n            \"isThumbnail\": false,\r\n            \"id\": 4,\r\n            \"url\": \"https://firebasestorage.googleapis.com/v0/b/b2bshop-d0961.appspot.com/o/10747be1-e4e9-454d-81e2-c132dbe3b860.jpg?alt=media\"\r\n        },\r\n        {\r\n            \"isThumbnail\": false,\r\n            \"url\": \"https://firebasestorage.googleapis.com/v0/b/b2bshop-d0961.appspot.com/o/10747be1-e4e9-454d-81e2-c132dbe3b860.jpg?alt=media\"\r\n        }\r\n    ],\r\n    \"code\": \"codemuz code!\",\r\n    \"salesPrice\": 17500.0,\r\n    \"vatRate\": 0.0,\r\n    \"description\": \"codemuz code!\",\r\n    \"active\": true,\r\n    \"grossPrice\": 20000.0,\r\n    \"name\": \"codemuz code!\",\r\n    \"id\": 2,\r\n    \"stock\": 55,\r\n    \"category\": {\r\n        \"name\": \"Bilgisayar\",\r\n        \"parentCategory\": 1,\r\n        \"id\": 2,\r\n        \"isActive\": true,\r\n        \"subCategories\": [\r\n            {\r\n                \"name\": \"Oyun Bilgisayarı\",\r\n                \"parentCategory\": 2,\r\n                \"id\": 4,\r\n                \"isActive\": true,\r\n                \"subCategories\": []\r\n            },\r\n            {\r\n                \"name\": \"İş Bilgisayarı\",\r\n                \"parentCategory\": 2,\r\n                \"id\": 5,\r\n                \"isActive\": true,\r\n                \"subCategories\": []\r\n            }\r\n        ]\r\n    },\r\n    \"brand\": {\r\n        \"name\": \"Samsung\",\r\n        \"id\": 2\r\n    }\r\n}",
							"options": {
								"raw": {
									"language": "json"
								}
							}
						},
						"url": {
							"raw": "{{baseurl}}/product/2",
							"host": [
								"{{baseurl}}"
							],
							"path": [
								"product",
								"2"
							]
						}
					},
					"response": []
				},
				{
					"name": "delete Product",
					"request": {
						"auth": {
							"type": "bearer",
							"bearer": [
								{
									"key": "token",
									"value": "{{bearer_token}}",
									"type": "string"
								}
							]
						},
						"method": "DELETE",
						"header": [],
						"body": {
							"mode": "raw",
							"raw": "",
							"options": {
								"raw": {
									"language": "json"
								}
							}
						},
						"url": {
							"raw": "{{baseurl}}/product/1",
							"host": [
								"{{baseurl}}"
							],
							"path": [
								"product",
								"1"
							]
						}
					},
					"response": []
				}
			]
		},
		{
			"name": "Brand",
			"item": [
				{
					"name": "get AllBrands",
					"protocolProfileBehavior": {
						"disableBodyPruning": true
					},
					"request": {
						"auth": {
							"type": "bearer",
							"bearer": [
								{
									"key": "token",
									"value": "{{bearer_token}}",
									"type": "string"
								}
							]
						},
						"method": "GET",
						"header": [],
						"body": {
							"mode": "raw",
							"raw": "",
							"options": {
								"raw": {
									"language": "json"
								}
							}
						},
						"url": {
							"raw": "{{baseurl}}/brand",
							"host": [
								"{{baseurl}}"
							],
							"path": [
								"brand"
							]
						}
					},
					"response": []
				},
				{
					"name": "get BrandById",
					"request": {
						"auth": {
							"type": "bearer",
							"bearer": [
								{
									"key": "token",
									"value": "{{bearer_token}}",
									"type": "string"
								}
							]
						},
						"method": "GET",
						"header": [],
						"url": {
							"raw": "{{baseurl}}/brand/1",
							"host": [
								"{{baseurl}}"
							],
							"path": [
								"brand",
								"1"
							]
						}
					},
					"response": []
				},
				{
					"name": "create singleBrand",
					"request": {
						"auth": {
							"type": "bearer",
							"bearer": [
								{
									"key": "token",
									"value": "{{bearer_token}}",
									"type": "string"
								}
							]
						},
						"method": "POST",
						"header": [],
						"body": {
							"mode": "raw",
							"raw": "{\r\n    \"name\":\"Monster\"\r\n}",
							"options": {
								"raw": {
									"language": "json"
								}
							}
						},
						"url": {
							"raw": "{{baseurl}}/brand",
							"host": [
								"{{baseurl}}"
							],
							"path": [
								"brand"
							]
						}
					},
					"response": []
				},
				{
					"name": "create multipleBrands",
					"request": {
						"auth": {
							"type": "bearer",
							"bearer": [
								{
									"key": "token",
									"value": "{{bearer_token}}",
									"type": "string"
								}
							]
						},
						"method": "POST",
						"header": [],
						"body": {
							"mode": "raw",
							"raw": "[\r\n    {\r\n        \"name\": \"Apple\"\r\n    },\r\n    {\r\n        \"name\": \"Samsung\"\r\n    },\r\n    {\r\n        \"name\": \"Nike\"\r\n    },\r\n    {\r\n        \"name\": \"Adidas\"\r\n    },\r\n    {\r\n        \"name\": \"Monster\"\r\n    },\r\n    {\r\n        \"name\": \"Hp\"\r\n    },\r\n    {\r\n        \"name\": \"Msi\"\r\n    },\r\n    {\r\n        \"name\": \"Dell\"\r\n    }\r\n]",
							"options": {
								"raw": {
									"language": "json"
								}
							}
						},
						"url": {
							"raw": "{{baseurl}}/brand",
							"host": [
								"{{baseurl}}"
							],
							"path": [
								"brand"
							]
						}
					},
					"response": []
				},
				{
					"name": "update BrandById",
					"request": {
						"auth": {
							"type": "bearer",
							"bearer": [
								{
									"key": "token",
									"value": "{{bearer_token}}",
									"type": "string"
								}
							]
						},
						"method": "PUT",
						"header": [],
						"body": {
							"mode": "raw",
							"raw": "{\r\n        \"name\": \"Monster\",\r\n        \"id\": 2\r\n    }",
							"options": {
								"raw": {
									"language": "json"
								}
							}
						},
						"url": {
							"raw": "{{baseurl}}/brand/2",
							"host": [
								"{{baseurl}}"
							],
							"path": [
								"brand",
								"2"
							]
						}
					},
					"response": []
				},
				{
					"name": "delete Brand",
					"request": {
						"auth": {
							"type": "bearer",
							"bearer": [
								{
									"key": "token",
									"value": "{{bearer_token}}",
									"type": "string"
								}
							]
						},
						"method": "DELETE",
						"header": [],
						"body": {
							"mode": "raw",
							"raw": "",
							"options": {
								"raw": {
									"language": "json"
								}
							}
						},
						"url": {
							"raw": "{{baseurl}}/brand/1",
							"host": [
								"{{baseurl}}"
							],
							"path": [
								"brand",
								"1"
							]
						}
					},
					"response": []
				}
			]
		},
		{
			"name": "Category",
			"item": [
				{
					"name": "get AllCategories",
					"protocolProfileBehavior": {
						"disableBodyPruning": true
					},
					"request": {
						"auth": {
							"type": "bearer",
							"bearer": [
								{
									"key": "token",
									"value": "{{bearer_token}}",
									"type": "string"
								}
							]
						},
						"method": "GET",
						"header": [],
						"body": {
							"mode": "raw",
							"raw": "",
							"options": {
								"raw": {
									"language": "json"
								}
							}
						},
						"url": {
							"raw": "{{baseurl}}/category",
							"host": [
								"{{baseurl}}"
							],
							"path": [
								"category"
							]
						}
					},
					"response": []
				},
				{
					"name": "get CategoryById",
					"request": {
						"auth": {
							"type": "bearer",
							"bearer": [
								{
									"key": "token",
									"value": "{{bearer_token}}",
									"type": "string"
								}
							]
						},
						"method": "GET",
						"header": [],
						"url": {
							"raw": "{{baseurl}}/category/6",
							"host": [
								"{{baseurl}}"
							],
							"path": [
								"category",
								"6"
							]
						}
					},
					"response": []
				},
				{
					"name": "create singleCategory",
					"request": {
						"auth": {
							"type": "bearer",
							"bearer": [
								{
									"key": "token",
									"value": "{{bearer_token}}",
									"type": "string"
								}
							]
						},
						"method": "POST",
						"header": [],
						"body": {
							"mode": "raw",
							"raw": "{\r\n    \"name\": \"Elektronik\",\r\n    \"active\": true,\r\n    \"parentCategoryId\": null\r\n}",
							"options": {
								"raw": {
									"language": "json"
								}
							}
						},
						"url": {
							"raw": "{{baseurl}}/category",
							"host": [
								"{{baseurl}}"
							],
							"path": [
								"category"
							]
						}
					},
					"response": []
				},
				{
					"name": "create multipleCategories",
					"request": {
						"auth": {
							"type": "bearer",
							"bearer": [
								{
									"key": "token",
									"value": "{{bearer_token}}",
									"type": "string"
								}
							]
						},
						"method": "POST",
						"header": [],
						"body": {
							"mode": "raw",
							"raw": "[\r\n    {\r\n        \"name\": \"name of product1\",\r\n        \"description\": \"description of product1\",\r\n        \"salesPrice\": 47.0,\r\n        \"grossPrice\": 54.0,\r\n        \"vatRate\": 7,\r\n        \"code\": \"123asdwq\",\r\n        \"shop\": {\r\n            \"tenantId\": 1\r\n        },\r\n        \"gtin\": \"5445678901061\",\r\n        \"stock\": 8,\r\n        \"isActive\": true\r\n    },\r\n    {\r\n        \"name\": \"name of product2\",\r\n        \"description\": \"description of product2\",\r\n        \"salesPrice\": 37.0,\r\n        \"grossPrice\": 123.0,\r\n        \"vatRate\": 3,\r\n        \"code\": \"5123wq\",\r\n        \"shop\": {\r\n            \"tenantId\": 2\r\n        },\r\n        \"gtin\": \"1845123901001\",\r\n        \"stock\": 76,\r\n        \"isActive\": true\r\n    },\r\n    {\r\n        \"name\": \"name of product3\",\r\n        \"description\": \"description of product3\",\r\n        \"salesPrice\": 49.0,\r\n        \"grossPrice\": 56.0,\r\n        \"vatRate\": 12,\r\n        \"code\": \"asd123asd\",\r\n        \"shop\": {\r\n            \"tenantId\": 3\r\n        },\r\n        \"gtin\": \"5325678901001\",\r\n        \"stock\": 89,\r\n        \"isActive\": true\r\n    },\r\n    {\r\n        \"name\": \"name of product4\",\r\n        \"description\": \"description of product4\",\r\n        \"salesPrice\": 97.79,\r\n        \"grossPrice\": 123.56,\r\n        \"vatRate\": 31,\r\n        \"code\": \"gcdff213asd\",\r\n        \"shop\": {\r\n            \"tenantId\": 1\r\n        },\r\n        \"gtin\": \"1845523401001\",\r\n        \"stock\": 74,\r\n        \"isActive\": true\r\n    },\r\n    {\r\n        \"name\": \"name of product5\",\r\n        \"description\": \"description of product5\",\r\n        \"salesPrice\": 7.97,\r\n        \"grossPrice\": 17.46,\r\n        \"vatRate\": 24,\r\n        \"code\": \"ghjfgwr\",\r\n        \"shop\": {\r\n            \"tenantId\": 2\r\n        },\r\n        \"gtin\": \"18456784353054\",\r\n        \"stock\": 35,\r\n        \"isActive\": true\r\n    },\r\n    {\r\n        \"name\": \"name of product6\",\r\n        \"description\": \"description of product6\",\r\n        \"salesPrice\": 55.45,\r\n        \"grossPrice\": 61.78,\r\n        \"vatRate\": 14,\r\n        \"code\": \"asdasdwq\",\r\n        \"shop\": {\r\n            \"tenantId\": 4\r\n        },\r\n        \"gtin\": \"1235678901007\",\r\n        \"stock\": 75,\r\n        \"isActive\": true\r\n    },\r\n    {\r\n        \"name\": \"name of product7\",\r\n        \"description\": \"description of product7\",\r\n        \"salesPrice\": 117.09,\r\n        \"grossPrice\": 137.79,\r\n        \"vatRate\": 10,\r\n        \"code\": \"lkşçjkl\",\r\n        \"shop\": {\r\n            \"tenantId\": 3\r\n        },\r\n        \"gtin\": \"7645678901562\",\r\n        \"stock\": 63,\r\n        \"isActive\": true\r\n    },\r\n    {\r\n        \"name\": \"name of product8\",\r\n        \"description\": \"description of product8\",\r\n        \"salesPrice\": 67.3,\r\n        \"grossPrice\": 74.7,\r\n        \"vatRate\": 11,\r\n        \"code\": \"gdfgdfwq\",\r\n        \"shop\": {\r\n            \"tenantId\": 4\r\n        },\r\n        \"gtin\": \"9655678901046\",\r\n        \"stock\": 45,\r\n        \"isActive\": true\r\n    },\r\n    {\r\n        \"name\": \"name of product9\",\r\n        \"description\": \"description of product9\",\r\n        \"salesPrice\": 63.06,\r\n        \"grossPrice\": 68.07,\r\n        \"vatRate\": 13,\r\n        \"code\": \"jgfhwe213\",\r\n        \"shop\": {\r\n            \"tenantId\": 2\r\n        },\r\n        \"gtin\": \"1845678901001\",\r\n        \"stock\": 7,\r\n        \"isActive\": true\r\n    }\r\n]\r\n",
							"options": {
								"raw": {
									"language": "json"
								}
							}
						},
						"url": {
							"raw": "{{baseurl}}/category",
							"host": [
								"{{baseurl}}"
							],
							"path": [
								"category"
							]
						}
					},
					"response": []
				},
				{
					"name": "update CategoryById",
					"request": {
						"auth": {
							"type": "bearer",
							"bearer": [
								{
									"key": "token",
									"value": "{{bearer_token}}",
									"type": "string"
								}
							]
						},
						"method": "PUT",
						"header": [],
						"body": {
							"mode": "raw",
							"raw": "{\r\n    \"id\": 1,\r\n    \"name\": \"test for update name of product1\",\r\n    \"description\": \"test for update description of product1\",\r\n    \"salesPrice\": 47.0,\r\n    \"grossPrice\": 54.0,\r\n    \"vatRate\": 7.0,\r\n    \"code\": \"123asdwq\",\r\n    \"shop\": {\r\n        \"tenantId\": 1\r\n    },\r\n    \"gtin\": \"test for update 5445678901061\",\r\n    \"stock\": 7,\r\n    \"active\": true\r\n}",
							"options": {
								"raw": {
									"language": "json"
								}
							}
						},
						"url": {
							"raw": "{{baseurl}}/category/1",
							"host": [
								"{{baseurl}}"
							],
							"path": [
								"category",
								"1"
							]
						}
					},
					"response": []
				},
				{
					"name": "delete Category",
					"request": {
						"auth": {
							"type": "bearer",
							"bearer": [
								{
									"key": "token",
									"value": "{{bearer_token}}",
									"type": "string"
								}
							]
						},
						"method": "DELETE",
						"header": [],
						"body": {
							"mode": "raw",
							"raw": "",
							"options": {
								"raw": {
									"language": "json"
								}
							}
						},
						"url": {
							"raw": "{{baseurl}}/category/1",
							"host": [
								"{{baseurl}}"
							],
							"path": [
								"category",
								"1"
							]
						}
					},
					"response": []
				}
			]
		},
		{
			"name": "Image",
			"item": [
				{
					"name": "addImages to Product",
					"request": {
						"auth": {
							"type": "bearer",
							"bearer": [
								{
									"key": "token",
									"value": "{{bearer_token}}",
									"type": "string"
								}
							]
						},
						"method": "POST",
						"header": [
							{
								"key": "Authorization",
								"value": "Bearer eyJhbGciOiJIUzI1NiJ9.eyJzdWIiOiJoYXRpY2UiLCJpYXQiOjE3MTYyOTIwMDMsImV4cCI6MTcxNjI5NTYwM30.yWqJ48Q9jF74Di18PCaJz3YWcpNai-V1fD6kBqrHuTA"
							}
						],
						"body": {
							"mode": "formdata",
							"formdata": [
								{
									"key": "file",
									"type": "file",
									"src": [
										"postman-cloud:///1ef1881e-7251-4670-948c-1b38054e1cb9",
										"postman-cloud:///1ef1881b-dbf6-46a0-b75b-3c7a95d0eb96"
									]
								}
							]
						},
						"url": {
							"raw": "{{baseurl}}/image",
							"host": [
								"{{baseurl}}"
							],
							"path": [
								"image"
							]
						}
					},
					"response": []
				}
			]
		},
		{
			"name": "Basket",
			"item": [
				{
					"name": "get Basket",
					"protocolProfileBehavior": {
						"disableBodyPruning": true
					},
					"request": {
						"auth": {
							"type": "bearer",
							"bearer": [
								{
									"key": "token",
									"value": "{{bearer_token}}",
									"type": "string"
								}
							]
						},
						"method": "GET",
						"header": [],
						"body": {
							"mode": "raw",
							"raw": "",
							"options": {
								"raw": {
									"language": "json"
								}
							}
						},
						"url": {
							"raw": "{{baseurl}}/basket",
							"host": [
								"{{baseurl}}"
							],
							"path": [
								"basket"
							]
						}
					},
					"response": []
				},
				{
					"name": "get BasketById",
					"request": {
						"auth": {
							"type": "bearer",
							"bearer": [
								{
									"key": "token",
									"value": "{{bearer_token}}",
									"type": "string"
								}
							]
						},
						"method": "GET",
						"header": [],
						"url": {
							"raw": "{{baseurl}}/basket/7",
							"host": [
								"{{baseurl}}"
							],
							"path": [
								"basket",
								"7"
							]
						}
					},
					"response": []
				},
				{
					"name": "addItemToBasket",
					"request": {
						"auth": {
							"type": "bearer",
							"bearer": [
								{
									"key": "token",
									"value": "{{bearer_token}}",
									"type": "string"
								}
							]
						},
						"method": "POST",
						"header": [],
						"body": {
							"mode": "raw",
							"raw": "{\r\n    \"productId\": 1,\r\n    \"quantity\": 6,\r\n    \"updateQuantity\": true\r\n}",
							"options": {
								"raw": {
									"language": "json"
								}
							}
						},
						"url": {
							"raw": "{{baseurl}}/basket/addItem",
							"host": [
								"{{baseurl}}"
							],
							"path": [
								"basket",
								"addItem"
							]
						}
					},
					"response": []
				},
				{
					"name": "removeItemFromTheBasket",
					"request": {
						"auth": {
							"type": "bearer",
							"bearer": [
								{
									"key": "token",
									"value": "{{bearer_token}}",
									"type": "string"
								}
							]
						},
						"method": "POST",
						"header": [],
						"body": {
							"mode": "raw",
							"raw": "{\r\n    \"productId\": 4\r\n}",
							"options": {
								"raw": {
									"language": "json"
								}
							}
						},
						"url": {
							"raw": "{{baseurl}}/basket/removeItem",
							"host": [
								"{{baseurl}}"
							],
							"path": [
								"basket",
								"removeItem"
							]
						}
					},
					"response": []
				},
				{
					"name": "cleanBasket",
					"request": {
						"auth": {
							"type": "bearer",
							"bearer": [
								{
									"key": "token",
									"value": "{{bearer_token}}",
									"type": "string"
								}
							]
						},
						"method": "POST",
						"header": [],
						"body": {
							"mode": "raw",
							"raw": "",
							"options": {
								"raw": {
									"language": "json"
								}
							}
						},
						"url": {
							"raw": "{{baseurl}}/basket/cleanBasket",
							"host": [
								"{{baseurl}}"
							],
							"path": [
								"basket",
								"cleanBasket"
							]
						}
					},
					"response": []
				},
				{
					"name": "delete Basket",
					"request": {
						"auth": {
							"type": "bearer",
							"bearer": [
								{
									"key": "token",
									"value": "{{bearer_token}}",
									"type": "string"
								}
							]
						},
						"method": "DELETE",
						"header": [],
						"body": {
							"mode": "raw",
							"raw": "",
							"options": {
								"raw": {
									"language": "json"
								}
							}
						},
						"url": {
							"raw": "{{baseurl}}/basket/1",
							"host": [
								"{{baseurl}}"
							],
							"path": [
								"basket",
								"1"
							]
						}
					},
					"response": []
				}
			]
		},
		{
			"name": "Order",
			"item": [
				{
					"name": "get AllOrders",
					"protocolProfileBehavior": {
						"disableBodyPruning": true
					},
					"request": {
						"auth": {
							"type": "bearer",
							"bearer": [
								{
									"key": "token",
									"value": "{{bearer_token}}",
									"type": "string"
								}
							]
						},
						"method": "GET",
						"header": [],
						"body": {
							"mode": "raw",
							"raw": "",
							"options": {
								"raw": {
									"language": "json"
								}
							}
						},
						"url": {
							"raw": "{{baseurl}}/order",
							"host": [
								"{{baseurl}}"
							],
							"path": [
								"order"
							]
						}
					},
					"response": []
				},
				{
					"name": "get OrderById",
					"request": {
						"auth": {
							"type": "bearer",
							"bearer": [
								{
									"key": "token",
									"value": "{{bearer_token}}",
									"type": "string"
								}
							]
						},
						"method": "GET",
						"header": [],
						"url": {
							"raw": "{{baseurl}}/order/1",
							"host": [
								"{{baseurl}}"
							],
							"path": [
								"order",
								"1"
							]
						}
					},
					"response": []
				},
				{
					"name": "create singleOrder",
					"request": {
						"auth": {
							"type": "bearer",
							"bearer": [
								{
									"key": "token",
									"value": "{{bearer_token}}",
									"type": "string"
								}
							]
						},
						"method": "POST",
						"header": [],
						"body": {
							"mode": "raw",
							"raw": "{\r\n    \"orderNote\": \"Good job!\",\r\n    \"basketId\": 1,\r\n    \"invoiceAddressId\": 1,\r\n    \"receiverAddressId\": 1\r\n}",
							"options": {
								"raw": {
									"language": "json"
								}
							}
						},
						"url": {
							"raw": "{{baseurl}}/order",
							"host": [
								"{{baseurl}}"
							],
							"path": [
								"order"
							]
						}
					},
					"response": []
				},
				{
					"name": "create multipleOrders",
					"request": {
						"auth": {
							"type": "bearer",
							"bearer": [
								{
									"key": "token",
									"value": "{{bearer_token}}",
									"type": "string"
								}
							]
						},
						"method": "POST",
						"header": [],
						"body": {
							"mode": "raw",
							"raw": "[\r\n    {\r\n        \"user\": {\r\n            \"id\": 8\r\n        },\r\n        \"product\": {\r\n            \"id\": 2\r\n        },\r\n        \"quantity\": 2\r\n    },\r\n    {\r\n        \"user\": {\r\n            \"id\": 8\r\n        },\r\n        \"product\": {\r\n            \"id\": 5\r\n        },\r\n        \"quantity\": 4\r\n    }\r\n]",
							"options": {
								"raw": {
									"language": "json"
								}
							}
						},
						"url": {
							"raw": "{{baseurl}}/order",
							"host": [
								"{{baseurl}}"
							],
							"path": [
								"order"
							]
						}
					},
					"response": []
				},
				{
					"name": "update OrderById",
					"request": {
						"auth": {
							"type": "bearer",
							"bearer": [
								{
									"key": "token",
									"value": "{{bearer_token}}",
									"type": "string"
								}
							]
						},
						"method": "PUT",
						"header": [],
						"body": {
							"mode": "raw",
							"raw": "{\r\n    \"id\": 8,\r\n    \"customer\": {\r\n        \"tenantId\": 1,\r\n        \"name\": \"first customer\",\r\n        \"email\": \"firstcustomer@mail.com\",\r\n        \"shop\": {\r\n            \"tenantId\": 1,\r\n            \"name\": \"first shop\",\r\n            \"email\": \"firstshop@mail.com\",\r\n            \"phoneNumber\": \"05678478961\",\r\n            \"vatNumber\": \"1 vatNumber\",\r\n            \"aboutUs\": \"1 aboutUs\",\r\n            \"privacyPolicy\": \"1 privacyPolicy\"\r\n        },\r\n        \"vatNumber\": \"first vatNumber\",\r\n        \"phoneNumber\": \"05678478961\",\r\n        \"active\": true\r\n    },\r\n    \"orderNumber\": \"124052400\",\r\n    \"orderNote\": \"test for new create order\",\r\n    \"orderItems\": [\r\n        {\r\n            \"id\": 8,\r\n            \"refProductId\": 40,\r\n            \"name\": \"Hakan'in Monsteri\",\r\n            \"salesPrice\": 9999.0,\r\n            \"grossPrice\": 9999.0,\r\n            \"quantity\": 2,\r\n            \"images\": [\r\n                {\r\n                    \"id\": 72,\r\n                    \"url\": \"https://firebasestorage.googleapis.com/v0/b/b2bshop-d0961.appspot.com/o/9ad184b0-d0ff-4bf9-906b-9bd1b5fbbf9e.jpg?alt=media\",\r\n                    \"createdBy\": null,\r\n                    \"isThumbnail\": null\r\n                },\r\n                {\r\n                    \"id\": 73,\r\n                    \"url\": \"https://firebasestorage.googleapis.com/v0/b/b2bshop-d0961.appspot.com/o/10747be1-e4e9-454d-81e2-c132dbe3b860.jpg?alt=media\",\r\n                    \"createdBy\": null,\r\n                    \"isThumbnail\": null\r\n                }\r\n            ]\r\n        }\r\n    ],\r\n    \"orderDate\": \"2024-05-23T21:54:41.955+00:00\",\r\n    \"orderStatus\": {\r\n        \"id\": 3,\r\n        \"status\": \"IPTAL_EDILDI\"\r\n    },\r\n    \"createdBy\": {\r\n        \"id\": 7,\r\n        \"name\": \"Hatice\",\r\n        \"username\": \"hatice\",\r\n        \"password\": \"$2a$10$P9WVoByidM7Kik.1m7qkXuFgPPUXVSqsfs9QBh6VbLYqYHwmdA7KO\",\r\n        \"email\": \"hatice@email.com\",\r\n        \"phoneNumber\": \"05369874505\",\r\n        \"authorities\": [\r\n            \"ROLE_CUSTOMER_USER\"\r\n        ],\r\n        \"shop\": null,\r\n        \"customer\": {\r\n            \"tenantId\": 1,\r\n            \"name\": \"first customer\",\r\n            \"email\": \"firstcustomer@mail.com\",\r\n            \"shop\": {\r\n                \"tenantId\": 1,\r\n                \"name\": \"first shop\",\r\n                \"email\": \"firstshop@mail.com\",\r\n                \"phoneNumber\": \"05678478961\",\r\n                \"vatNumber\": \"1 vatNumber\",\r\n                \"aboutUs\": \"1 aboutUs\",\r\n                \"privacyPolicy\": \"1 privacyPolicy\"\r\n            },\r\n            \"vatNumber\": \"first vatNumber\",\r\n            \"phoneNumber\": \"05678478961\",\r\n            \"active\": true\r\n        },\r\n        \"accountNonLocked\": true,\r\n        \"accountNonExpired\": true,\r\n        \"credentialsNonExpired\": true,\r\n        \"enabled\": true,\r\n        \"active\": true\r\n    },\r\n    \"invoiceAddress\": {\r\n        \"id\": 1,\r\n        \"customer\": {\r\n            \"tenantId\": 1,\r\n            \"name\": \"first customer\",\r\n            \"email\": \"firstcustomer@mail.com\",\r\n            \"shop\": {\r\n                \"tenantId\": 1,\r\n                \"name\": \"first shop\",\r\n                \"email\": \"firstshop@mail.com\",\r\n                \"phoneNumber\": \"05678478961\",\r\n                \"vatNumber\": \"1 vatNumber\",\r\n                \"aboutUs\": \"1 aboutUs\",\r\n                \"privacyPolicy\": \"1 privacyPolicy\"\r\n            },\r\n            \"vatNumber\": \"first vatNumber\",\r\n            \"phoneNumber\": \"05678478961\",\r\n            \"active\": true\r\n        },\r\n        \"country\": null,\r\n        \"title\": \"Bizim ev\",\r\n        \"city\": \"İstanbul\",\r\n        \"addressLine\": \"Fatih Mahallesi İnönü Caddesi No:45 Daire: 3, Beyoğlu, İstanbul\"\r\n    },\r\n    \"receiverAddress\": {\r\n        \"id\": 1,\r\n        \"customer\": {\r\n            \"tenantId\": 1,\r\n            \"name\": \"first customer\",\r\n            \"email\": \"firstcustomer@mail.com\",\r\n            \"shop\": {\r\n                \"tenantId\": 1,\r\n                \"name\": \"first shop\",\r\n                \"email\": \"firstshop@mail.com\",\r\n                \"phoneNumber\": \"05678478961\",\r\n                \"vatNumber\": \"1 vatNumber\",\r\n                \"aboutUs\": \"1 aboutUs\",\r\n                \"privacyPolicy\": \"1 privacyPolicy\"\r\n            },\r\n            \"vatNumber\": \"first vatNumber\",\r\n            \"phoneNumber\": \"05678478961\",\r\n            \"active\": true\r\n        },\r\n        \"country\": null,\r\n        \"title\": \"Bizim ev\",\r\n        \"city\": \"İstanbul\",\r\n        \"addressLine\": \"Fatih Mahallesi İnönü Caddesi No:45 Daire: 3, Beyoğlu, İstanbul\"\r\n    },\r\n    \"totalPrice\": 19998.0,\r\n    \"withoutTaxPrice\": 19998.0,\r\n    \"totalTax\": 0.0\r\n}",
							"options": {
								"raw": {
									"language": "json"
								}
							}
						},
						"url": {
							"raw": "{{baseurl}}/order/8",
							"host": [
								"{{baseurl}}"
							],
							"path": [
								"order",
								"8"
							]
						}
					},
					"response": []
				},
				{
					"name": "delete Order",
					"request": {
						"auth": {
							"type": "bearer",
							"bearer": [
								{
									"key": "token",
									"value": "{{bearer_token}}",
									"type": "string"
								}
							]
						},
						"method": "DELETE",
						"header": [],
						"body": {
							"mode": "raw",
							"raw": "",
							"options": {
								"raw": {
									"language": "json"
								}
							}
						},
						"url": {
							"raw": "{{baseurl}}/order/1",
							"host": [
								"{{baseurl}}"
							],
							"path": [
								"order",
								"1"
							]
						}
					},
					"response": []
				}
			]
		},
		{
			"name": "Address",
			"item": [
				{
					"name": "get AllAddresses",
					"protocolProfileBehavior": {
						"disableBodyPruning": true
					},
					"request": {
						"auth": {
							"type": "bearer",
							"bearer": [
								{
									"key": "token",
									"value": "{{bearer_token}}",
									"type": "string"
								}
							]
						},
						"method": "GET",
						"header": [],
						"body": {
							"mode": "raw",
							"raw": "",
							"options": {
								"raw": {
									"language": "json"
								}
							}
						},
						"url": {
							"raw": "{{baseurl}}/address",
							"host": [
								"{{baseurl}}"
							],
							"path": [
								"address"
							]
						}
					},
					"response": []
				},
				{
					"name": "get AddressById",
					"request": {
						"auth": {
							"type": "bearer",
							"bearer": [
								{
									"key": "token",
									"value": "{{bearer_token}}",
									"type": "string"
								}
							]
						},
						"method": "GET",
						"header": [],
						"url": {
							"raw": "{{baseurl}}/address/1",
							"host": [
								"{{baseurl}}"
							],
							"path": [
								"address",
								"1"
							]
						}
					},
					"response": []
				},
				{
					"name": "create singleAddress",
					"request": {
						"auth": {
							"type": "bearer",
							"bearer": [
								{
									"key": "token",
									"value": "{{bearer_token}}",
									"type": "string"
								}
							]
						},
						"method": "POST",
						"header": [],
						"body": {
							"mode": "raw",
							"raw": "{\r\n    \"countryId\": 1,\r\n    \"title\": \"Bizim ev\",\r\n    \"city\": \"İstanbul\",\r\n    \"addressLine\": \"Fatih Mahallesi İnönü Caddesi No:45 Daire: 3, Beyoğlu, İstanbul\"\r\n}",
							"options": {
								"raw": {
									"language": "json"
								}
							}
						},
						"url": {
							"raw": "{{baseurl}}/address",
							"host": [
								"{{baseurl}}"
							],
							"path": [
								"address"
							]
						}
					},
					"response": []
				},
				{
					"name": "create multipleAddresses",
					"request": {
						"auth": {
							"type": "bearer",
							"bearer": [
								{
									"key": "token",
									"value": "{{bearer_token}}",
									"type": "string"
								}
							]
						},
						"method": "POST",
						"header": [],
						"body": {
							"mode": "raw",
							"raw": "[\r\n    {\r\n        \"user\": {\r\n            \"id\": 8\r\n        },\r\n        \"product\": {\r\n            \"id\": 2\r\n        },\r\n        \"quantity\": 2\r\n    },\r\n    {\r\n        \"user\": {\r\n            \"id\": 8\r\n        },\r\n        \"product\": {\r\n            \"id\": 5\r\n        },\r\n        \"quantity\": 4\r\n    }\r\n]",
							"options": {
								"raw": {
									"language": "json"
								}
							}
						},
						"url": {
							"raw": "{{baseurl}}/order",
							"host": [
								"{{baseurl}}"
							],
							"path": [
								"order"
							]
						}
					},
					"response": []
				},
				{
					"name": "update OrderById",
					"request": {
						"auth": {
							"type": "bearer",
							"bearer": [
								{
									"key": "token",
									"value": "{{bearer_token}}",
									"type": "string"
								}
							]
						},
						"method": "PUT",
						"header": [],
						"body": {
							"mode": "raw",
							"raw": "{\r\n    \"id\": 7,\r\n    \"user\": {\r\n        \"id\": 7        \r\n    },\r\n    \"product\": {\r\n        \"id\": 1        \r\n    },\r\n    \"quantity\": 13\r\n}",
							"options": {
								"raw": {
									"language": "json"
								}
							}
						},
						"url": {
							"raw": "{{baseurl}}/address/1",
							"host": [
								"{{baseurl}}"
							],
							"path": [
								"address",
								"1"
							]
						}
					},
					"response": []
				},
				{
					"name": "delete Basket",
					"request": {
						"auth": {
							"type": "bearer",
							"bearer": [
								{
									"key": "token",
									"value": "{{bearer_token}}",
									"type": "string"
								}
							]
						},
						"method": "DELETE",
						"header": [],
						"body": {
							"mode": "raw",
							"raw": "",
							"options": {
								"raw": {
									"language": "json"
								}
							}
						},
						"url": {
							"raw": "{{baseurl}}/address/1",
							"host": [
								"{{baseurl}}"
							],
							"path": [
								"address",
								"1"
							]
						}
					},
					"response": []
				}
			]
		},
		{
			"name": "Login",
			"item": [
				{
					"name": "loginWithSystemOwner",
					"event": [
						{
							"listen": "test",
							"script": {
								"exec": [
									"pm.test(\"Set Token!\", function () {",
									"    var jsonData = pm.response.json();",
									"    console.log(jsonData.token)",
									"    pm.collectionVariables.set(\"bearer_token\", jsonData.token);",
									"});"
								],
								"type": "text/javascript",
								"packages": {}
							}
						}
					],
					"request": {
						"method": "POST",
						"header": [],
						"body": {
							"mode": "raw",
							"raw": "{\r\n    \"username\": \"hakan\",\r\n    \"password\": \"pass\"\r\n}",
							"options": {
								"raw": {
									"language": "json"
								}
							}
						},
						"url": {
							"raw": "{{baseurl}}/login",
							"host": [
								"{{baseurl}}"
							],
							"path": [
								"login"
							]
						}
					},
					"response": []
				},
				{
					"name": "loginWithShopOwner",
					"event": [
						{
							"listen": "test",
							"script": {
								"exec": [
									"pm.test(\"Set Token!\", function () {",
									"    var jsonData = pm.response.json();",
									"    console.log(jsonData.token)",
									"    pm.collectionVariables.set(\"bearer_token\", jsonData.token);",
									"});"
								],
								"type": "text/javascript",
								"packages": {}
							}
						}
					],
					"request": {
						"method": "POST",
						"header": [],
						"body": {
							"mode": "raw",
							"raw": "{\r\n    \"tenantId\": 1,\r\n    \"username\": \"firstshop@mail.com\",\r\n    \"password\": \"password\"\r\n}",
							"options": {
								"raw": {
									"language": "json"
								}
							}
						},
						"url": {
							"raw": "{{baseurl}}/login",
							"host": [
								"{{baseurl}}"
							],
							"path": [
								"login"
							]
						}
					},
					"response": []
				},
				{
					"name": "loginWithCustomerUser",
					"event": [
						{
							"listen": "test",
							"script": {
								"exec": [
									"pm.test(\"Set Token!\", function () {",
									"    var jsonData = pm.response.json();",
									"    console.log(jsonData.token)",
									"    pm.collectionVariables.set(\"bearer_token\", jsonData.token);",
									"});"
								],
								"type": "text/javascript",
								"packages": {}
							}
						}
					],
					"request": {
						"method": "POST",
						"header": [],
						"body": {
							"mode": "raw",
							"raw": "{\r\n    \"tenantId\": 1,\r\n    \"username\": \"firstcustomer@mail.com\",\r\n    \"password\": \"password\"\r\n}",
							"options": {
								"raw": {
									"language": "json"
								}
							}
						},
						"url": {
							"raw": "{{baseurl}}/login",
							"host": [
								"{{baseurl}}"
							],
							"path": [
								"login"
							]
						}
					},
					"response": []
				}
			]
		},
		{
			"name": "Country",
			"item": [
				{
					"name": "get AllCountries",
					"protocolProfileBehavior": {
						"disableBodyPruning": true
					},
					"request": {
						"auth": {
							"type": "bearer",
							"bearer": [
								{
									"key": "token",
									"value": "{{bearer_token}}",
									"type": "string"
								}
							]
						},
						"method": "GET",
						"header": [],
						"body": {
							"mode": "raw",
							"raw": "",
							"options": {
								"raw": {
									"language": "json"
								}
							}
						},
						"url": {
							"raw": "{{baseurl}}/country",
							"host": [
								"{{baseurl}}"
							],
							"path": [
								"country"
							]
						}
					},
					"response": []
				}
			]
		},
		{
			"name": "Dashboard",
			"item": [
				{
					"name": "get Dashboard",
					"protocolProfileBehavior": {
						"disableBodyPruning": true
					},
					"request": {
						"auth": {
							"type": "bearer",
							"bearer": [
								{
									"key": "token",
									"value": "{{bearer_token}}",
									"type": "string"
								}
							]
						},
						"method": "GET",
						"header": [],
						"body": {
							"mode": "raw",
							"raw": "",
							"options": {
								"raw": {
									"language": "json"
								}
							}
						},
						"url": {
							"raw": "{{baseurl}}/dashboard",
							"host": [
								"{{baseurl}}"
							],
							"path": [
								"dashboard"
							]
						}
					},
					"response": []
				}
			]
		},
		{
			"name": "create systemOwners!!",
			"request": {
				"auth": {
					"type": "noauth"
				},
				"method": "POST",
				"header": [],
				"body": {
					"mode": "raw",
					"raw": "",
					"options": {
						"raw": {
							"language": "json"
						}
					}
				},
				"url": {
					"raw": "{{baseurl}}/user/createSystemOwners",
					"host": [
						"{{baseurl}}"
					],
					"path": [
						"user",
						"createSystemOwners"
					]
				}
			},
			"response": []
		}
	],
	"event": [
		{
			"listen": "prerequest",
			"script": {
				"type": "text/javascript",
				"packages": {},
				"exec": [
					""
				]
			}
		},
		{
			"listen": "test",
			"script": {
				"type": "text/javascript",
				"packages": {},
				"exec": [
					""
				]
			}
		}
	],
	"variable": [
		{
			"key": "baseurl",
			"value": "localhost:8080/api"
		},
		{
			"key": "bearer_token",
			"value": ""
		}
	]
}